dispatches_data/packages/synthetic_price/ARMA_pointer_2018_2021_to2045.csv
dispatches_data/packages/synthetic_price/ARMA_train.xml
dispatches_data/packages/synthetic_price/COPYRIGHT.md
dispatches_data/packages/synthetic_price/LICENSE.md
dispatches_data/packages/synthetic_price/Price_2018.csv
dispatches_data/packages/synthetic_price/Price_2019.csv
dispatches_data/packages/synthetic_price/Price_2020.csv
dispatches_data/packages/synthetic_price/Price_2021.csv
dispatches_data/packages/synthetic_price/README.md
dispatches_data/packages/synthetic_price/__init__.py
dispatches_synthetic_price_data-23.4.4.dist-info/METADATA
dispatches_synthetic_price_data-23.4.4.dist-info/WHEEL
dispatches_synthetic_price_data-23.4.4.dist-info/top_level.txt
dispatches_synthetic_price_data-23.4.4.dist-info/RECORD
