Metadata-Version: 2.1
Name: dispatches-synthetic-price-data
Version: 23.4.4
Requires-Dist: dispatches-data-packages (>=23.3.15.1)
